{
    "job": {
        "title": "Data Engineer - 100% Remote",
        "industry": "Information Technology and Services",
        "description": "Job Title: Data Engineer Position Type: Contract until December 2021 (2.5 Months) Location: 100% remote, no travel, prefer Central or East Coast location since a lot of the team onshore work East Coast. Primary Skills: 5+ years of developer/data engineer experience working specifically in Azure Python, Scala, SQL and/or Databricks hands on experience Requirements: At least 5+ years of developer/data engineer experience working specifically in Azure. Must have python, scala, SQL and/or databricks hands on experience. Should be independent worker but collaborate with necessary peers and deliver results incrementally by taking full ownership of tasks. Daily duties: 1.\u00a0\u00a0\u00a0\u00a0\u00a0Gen 1 to Gen 2 transition a)\u00a0\u00a0\u00a0\u00a0\u00a0Majority of their data pipelines are using Azure Data Lake Storage Gen 1 which is going to be deprecated by Microsoft b)\u00a0\u00a0\u00a0\u00a0\u00a0Hence they need to migrate this to ADLS Gen 2 version c)\u00a0\u00a0\u00a0\u00a0\u00a0Approximately, 155 data pipelines will be impacted from an ingestion pov and another 30 pipelines will also need to be updated in Refined data process 2.\u00a0\u00a0\u00a0\u00a0\u00a0Data Quality automation a)\u00a0\u00a0\u00a0\u00a0\u00a0Today, they have several notebooks and scripts that perform aggregate quality checks for multiple sources b)\u00a0\u00a0\u00a0\u00a0\u00a0Some of these need to be upgraded to use more current pipeline run information and also needs automation c)\u00a0\u00a0\u00a0\u00a0\u00a0They will utilize ADLSg2 to store this metadata for reporting and analysis 3.\u00a0\u00a0\u00a0\u00a0\u00a0Functions optimization and Vacuum implementation a)\u00a0\u00a0\u00a0\u00a0\u00a0There are Azure Functions based processes that needs update and optimization as each of them are running independently b)\u00a0\u00a0\u00a0\u00a0\u00a0Opportunity to modularize some of these functions and as a result reduce overhead on system resources",
        "employment_type": "CONTRACTOR",
        "date_posted": "2021-10-05T17:39:17.000Z"
    },
    "company": {
        "name": "Staffing Technologies",
        "link": "https://www.linkedin.com/company/staffing-technologies"
    },
    "education": {
        "required_credential": "bachelor degree"
    },
    "experience": {
        "months_of_experience": 60,
        "seniority_level": "Senior Level"
    },
    "salary": {
        "currency": null,
        "min_value": null,
        "max_value": null,
        "unit": null
    },
    "location": {
        "country": "US",
        "locality": "Boston",
        "region": "MA",
        "postal_code": "02118",
        "street_address": null,
        "latitude": 42.358994,
        "longitude": -71.05863
    }
}