{
    "job": {
        "title": "Senior Data Scientist",
        "industry": "Marketing and Advertising,Financial Services",
        "description": "Leading Healthcare firm is looking for an Analytics Lead to assist in achieving business growth. This is a great opportunity to have a tremendous impact on client success by utilizing your analytic skills and applying business insights. Responsibilities: Developing predictive models and test plans to support continuous improvement of campaign efforts using SAS/SQL/Python Work closely with internal and external stakeholders to develop KPI frameworks, interactive dashboards to optimize direct marketing\u00a0programs Performing quantitative analysis to predict customer behavior as well as market mix modeling Develop and deliver client presentations \u2013 including data analysis and written content Qualifications: 6+ years of experience in a data-driven role Advanced Excel experience; running statistical analysis and predictive models, developing financial models, running sensitivity analyses, automating tasks, etc. SQL, SAS, Python or other programming language experience Expertise with Tableau, Power BI, or other reporting/campaign management software",
        "employment_type": "FULL_TIME",
        "date_posted": "2021-08-25T17:21:18.000Z"
    },
    "company": {
        "name": "Intelletec",
        "link": "https://www.linkedin.com/company/intelletec-ltd"
    },
    "education": {
        "required_credential": "bachelor degree"
    },
    "experience": {
        "months_of_experience": 72,
        "seniority_level": "Senior Level"
    },
    "salary": {
        "currency": null,
        "min_value": null,
        "max_value": null,
        "unit": null
    },
    "location": {
        "country": "US",
        "locality": "Greater Boston",
        "region": null,
        "postal_code": "02119",
        "street_address": null,
        "latitude": 42.36041,
        "longitude": -71.05798
    }
}